[
    {
        "name": "Tubular",
        "access_rules": [
            ""
        ],
        "visibility_rules": [
            ""
        ],
        "children": [
            {
                "name": "Tubular - Goal",
                "sections": [
                    {
                        "name": "Normal Exit",
                        "ref": "Map/Tubular/Normal Exit"
                    }
                ],
                "map_locations": [
                    {
                        "map": "sw2_main",
                        "x": 1000,
                        "y": 808
                    }
                ]
            },
            {
                "name": "Tubular - Dragon Coins",
                "sections": [
                    {
                        "name": "Dragon Coins",
                        "ref": "Map/Tubular/Dragon Coins"
                    }
                ],
                "map_locations": [
                    {
                        "map": "sw2_main",
                        "x": 536,
                        "y": 240
                    },
                    {
                        "map": "sw2_main",
                        "x": 904,
                        "y": 304
                    },
                    {
                        "map": "sw2_main",
                        "x": 1112,
                        "y": 240
                    },
                    {
                        "map": "sw2_main",
                        "x": 1480,
                        "y": 288
                    },
                    {
                        "map": "sw2_main",
                        "x": 600,
                        "y": 720
                    },
                    {
                        "map": "sw2_main",
                        "x": 808,
                        "y": 704
                    }
                ]
            },
            {
                "name": "Tubular - Blocksanity - Powerup Block #1",
                "sections": [
                    {
                        "name": "Powerup Block #1",
                        "ref": "Map/Tubular/Powerup Block #1"
                    }
                ],
                "map_locations": [
                    {
                        "map": "sw2_main",
                        "x": 744,
                        "y": 296
                    }
                ]
            },
            {
                "name": "Tubular - Blocksanity - Coin Block #1",
                "sections": [
                    {
                        "name": "Coin Block #1",
                        "ref": "Map/Tubular/Coin Block #1"
                    }
                ],
                "map_locations": [
                    {
                        "map": "sw2_main",
                        "x": 904,
                        "y": 280
                    }
                ]
            },
            {
                "name": "Tubular - Blocksanity - Coin Block #2",
                "sections": [
                    {
                        "name": "Coin Block #2",
                        "ref": "Map/Tubular/Coin Block #2"
                    }
                ],
                "map_locations": [
                    {
                        "map": "sw2_main",
                        "x": 1112,
                        "y": 328
                    }
                ]
            },
            {
                "name": "Tubular - Blocksanity - Powerup Block #2",
                "sections": [
                    {
                        "name": "Powerup Block #2",
                        "ref": "Map/Tubular/Powerup Block #2"
                    }
                ],
                "map_locations": [
                    {
                        "map": "sw2_main",
                        "x": 1192,
                        "y": 248
                    }
                ]
            },
            {
                "name": "Tubular - Blocksanity - Coin Block #3",
                "sections": [
                    {
                        "name": "Coin Block #3",
                        "ref": "Map/Tubular/Coin Block #3"
                    }
                ],
                "map_locations": [
                    {
                        "map": "sw2_main",
                        "x": 1480,
                        "y": 344
                    }
                ]
            },
            {
                "name": "Tubular - Blocksanity - Coin Block #4",
                "sections": [
                    {
                        "name": "Coin Block #4",
                        "ref": "Map/Tubular/Coin Block #4"
                    }
                ],
                "map_locations": [
                    {
                        "map": "sw2_main",
                        "x": 1480,
                        "y": 248
                    }
                ]
            },
            {
                "name": "Tubular - Blocksanity - Powerup Block #3",
                "sections": [
                    {
                        "name": "Powerup Block #3",
                        "ref": "Map/Tubular/Powerup Block #3"
                    }
                ],
                "map_locations": [
                    {
                        "map": "sw2_main",
                        "x": 360,
                        "y": 760
                    }
                ]
            },
            {
                "name": "Tubular - Blocksanity - Multi Coin Block #1",
                "sections": [
                    {
                        "name": "Multi Coin Block #1",
                        "ref": "Map/Tubular/Multi Coin Block #1"
                    }
                ],
                "map_locations": [
                    {
                        "map": "sw2_main",
                        "x": 488,
                        "y": 664
                    }
                ]
            },
            {
                "name": "Tubular - Blocksanity - Coin Block #5",
                "sections": [
                    {
                        "name": "Coin Block #5",
                        "ref": "Map/Tubular/Coin Block #5"
                    }
                ],
                "map_locations": [
                    {
                        "map": "sw2_main",
                        "x": 600,
                        "y": 696
                    }
                ]
            },
            {
                "name": "Tubular - Blocksanity - Coin Block #6",
                "sections": [
                    {
                        "name": "Coin Block #6",
                        "ref": "Map/Tubular/Coin Block #6"
                    }
                ],
                "map_locations": [
                    {
                        "map": "sw2_main",
                        "x": 808,
                        "y": 760
                    }
                ]
            },
            {
                "name": "Tubular - Main room",
                "sections": [
                    {
                        "name": "Main room",
                        "ref": "Map/Tubular/Main room"
                    },
                    {
                        "name": "Normal Exit",
                        "ref": "Map/Tubular/Normal Exit"
                    },
                    {
                        "name": "Dragon Coins",
                        "ref": "Map/Tubular/Dragon Coins"
                    },
                    {
                        "name": "Powerup Block #1",
                        "ref": "Map/Tubular/Powerup Block #1"
                    },
                    {
                        "name": "Coin Block #1",
                        "ref": "Map/Tubular/Coin Block #1"
                    },
                    {
                        "name": "Coin Block #2",
                        "ref": "Map/Tubular/Coin Block #2"
                    },
                    {
                        "name": "Powerup Block #2",
                        "ref": "Map/Tubular/Powerup Block #2"
                    },
                    {
                        "name": "Coin Block #3",
                        "ref": "Map/Tubular/Coin Block #3"
                    },
                    {
                        "name": "Coin Block #4",
                        "ref": "Map/Tubular/Coin Block #4"
                    },
                    {
                        "name": "Powerup Block #3",
                        "ref": "Map/Tubular/Powerup Block #3"
                    },
                    {
                        "name": "Multi Coin Block #1",
                        "ref": "Map/Tubular/Multi Coin Block #1"
                    },
                    {
                        "name": "Coin Block #5",
                        "ref": "Map/Tubular/Coin Block #5"
                    },
                    {
                        "name": "Coin Block #6",
                        "ref": "Map/Tubular/Coin Block #6"
                    }
                ],
                "map_locations": [
                    {
                        "map": "sw2_main",
                        "x": 16,
                        "y": 16
                    }
                ]
            }
        ]
    }
]